concordia/__init__.py
concordia/constraints.py
concordia/library.py
concordia/solver.py
concordia_harmony-1.0.0.dist-info/LICENSE
concordia_harmony-1.0.0.dist-info/METADATA
concordia_harmony-1.0.0.dist-info/WHEEL
concordia_harmony-1.0.0.dist-info/top_level.txt
concordia_harmony-1.0.0.dist-info/RECORD
