Metadata-Version: 2.1
Name: concordia-harmony
Version: 1.0.0
License-File: LICENSE
Requires-Dist: music21
Requires-Dist: z3-solver
